auto_ms/__init__.py
auto_ms/main.py
auto_ms/modules/__init__.py
auto_ms/modules/gui.py
auto_ms/modules/handle_input.py
auto_ms/modules/parse.py
auto_ms/modules/process.py
auto_ms/testcases/__init__.py
auto_ms/testcases/tests.py
auto_ms-0.1.1.dist-info/DESCRIPTION.rst
auto_ms-0.1.1.dist-info/METADATA
auto_ms-0.1.1.dist-info/RECORD
auto_ms-0.1.1.dist-info/WHEEL
auto_ms-0.1.1.dist-info/entry_points.txt
auto_ms-0.1.1.dist-info/metadata.json
auto_ms-0.1.1.dist-info/top_level.txt
