Metadata-Version: 2.0
Name: auto-ms
Version: 0.1.1
Summary: Tools for processing MS output
Home-page: https://github.com/klim314/auto_ms
Author: klim314
Author-email: klim314@gmail.com
License: UNKNOWN
Platform: UNKNOWN
Classifier: Development Status :: 3 - Alpha
Classifier: Intended Audience :: Science/Research
Classifier: License :: OSI Approved :: MIT License
Classifier: Programming Language :: Python :: 3
Requires-Dist: numpy
Requires-Dist: openpyxl
Requires-Dist: pandas
